{
  "response": [
    {
      "maintainer": "0xSoul",
      "oem": "Google",
      "device": "Pixel 4 XL",
      "filename": "EvolutionX-14.0-20240718-coral-v9.2-Unofficial.zip",
      "download": "https://sourceforge.net/projects/evolutionx-floral/files/coral/14/EvolutionX-14.0-20240718-coral-v9.2-Unofficial.zip/download",
      "timestamp": 1721308135,
      "md5": "b9d5fae5a8a84d81e8c6c23e5d4eacfe",
      "sha256": "2fa9673e229002c7d074b5ddcdc02335c8b23e29327e945c1fe8b68731a13be9",
      "size": 2307165065,
      "version": "9.2",
      "buildtype": "Release",
      "forum": "https://xdaforums.com/t/rom-wireguard-kernelsu-evolution-x-9-0-pixel-4-4xl-floral-unofficial-27-05-2024.4670790/",
      "firmware": "TP1A.221005.002.B2",
      "paypal": "https://PayPal.me/0xSoul",
      "telegram": "https://telegram.me/EvoX9Unofficial"
    }
  ]
}
